[{"model": "comments.comment", "pk": 1, "fields": {"name": "\u5207\u5207\u5207", "email": "123@zjl.com", "url": "", "text": "\u7b2c\u4e00", "created_time": "2019-01-31T14:07:41.494Z", "post": 4}}, {"model": "comments.comment", "pk": 2, "fields": {"name": "zjl", "email": "u4@live.com", "url": "", "text": "\u7b2c\u4e8c", "created_time": "2019-01-31T14:07:54.295Z", "post": 4}}, {"model": "comments.comment", "pk": 3, "fields": {"name": "\u5c0f\u660e", "email": "1184671866@qq.com", "url": "", "text": "\u7b2c\u4e09", "created_time": "2019-01-31T14:08:14.141Z", "post": 4}}, {"model": "comments.comment", "pk": 4, "fields": {"name": "python", "email": "zjl@123.com", "url": "", "text": "11212", "created_time": "2019-01-31T14:14:09.401Z", "post": 4}}, {"model": "comments.comment", "pk": 5, "fields": {"name": "zjl", "email": "zjl@123.com", "url": "", "text": "11111", "created_time": "2019-01-31T14:19:08.036Z", "post": 3}}, {"model": "comments.comment", "pk": 6, "fields": {"name": "python", "email": "u4@live.com", "url": "", "text": "\u8428\u8fbe\u5b9e\u6253\u5b9e\u591a", "created_time": "2019-01-31T14:25:08.672Z", "post": 3}}, {"model": "comments.comment", "pk": 7, "fields": {"name": "\u8428\u8fbe\u65af", "email": "zjl@123.com", "url": "", "text": "\u554a\u98d2\u98d2\u98d2\u98d2\u7684", "created_time": "2019-02-01T02:57:29.651Z", "post": 3}}, {"model": "comments.comment", "pk": 8, "fields": {"name": "\u641e\u7b11", "email": "zjl@123.com", "url": "", "text": "22222222222222", "created_time": "2019-02-01T02:57:42.689Z", "post": 3}}, {"model": "comments.comment", "pk": 9, "fields": {"name": "\u56de\u9996\u638f", "email": "zxc@asd.com", "url": "", "text": "6666666666666666", "created_time": "2019-02-01T05:03:51.210Z", "post": 1}}, {"model": "comments.comment", "pk": 10, "fields": {"name": "\u6d41\u6c34", "email": "sdaf@163.com", "url": "", "text": "\u6740\u795e\u98ce", "created_time": "2019-02-10T14:34:32.480Z", "post": 3}}]